setup.cfg
setup.py
dot/__init__.py
dot/cli.py
dot/git.py
dot_cli.egg-info/PKG-INFO
dot_cli.egg-info/SOURCES.txt
dot_cli.egg-info/dependency_links.txt
dot_cli.egg-info/entry_points.txt
dot_cli.egg-info/not-zip-safe
dot_cli.egg-info/requires.txt
dot_cli.egg-info/top_level.txt