Metadata-Version: 1.1
Name: dot-cli
Version: 0.0.5
Summary: Lightweight tool for managing dotfiles with git and the command line.
Home-page: https://github.com/kylefrost/dot
Author: Kyle Frost
Author-email: kyle@kylefrost.me
License: GPLv3
Download-URL: https://github.com/kylefrost/dot-cli/tarball/0.0.5
Platform: any
Classifier: Development Status :: 5 - Production/Stable
Classifier: Environment :: Console
Classifier: Intended Audience :: Developers
Classifier: License :: OSI Approved :: GNU General Public License v3 (GPLv3)
Classifier: Operating System :: POSIX
Classifier: Operating System :: MacOS
Classifier: Operating System :: Unix
Classifier: Operating System :: Microsoft :: Windows
Classifier: Programming Language :: Python
Classifier: Programming Language :: Python :: 2
Classifier: Topic :: Software Development :: Libraries :: Python Modules
